<?xml version="1.0" encoding="utf-8" standalone='yes'?>
<data>
  <Worksheet Name="Sheet1">
    <Row>
        <Cell Type="String">First Name</Cell>
        <Cell Type="String">Last Name</Cell>
        <Cell Type="String">aeazeaze</Cell>
        <Cell Type="String">Phone Number</Cell>
    </Row>
    <Row>
        <Cell/>
        <Cell Type="String">Jones</Cell>
        <Cell Type="String">(425) 123-4567</Cell>
    </Row>
  </Worksheet>
  <Worksheet Name="Sheet2">
    <Row>
        <Cell Type="String">First Name</Cell>
        <Cell Type="String">Last Name</Cell>
        <Cell Type="String">Phone Number</Cell>
    </Row>
    <Row>
        <Cell Type="String">Melon</Cell>
        <Cell Type="String">Jones</Cell>
        <Cell Type="String">(425) 123-4567</Cell>
    </Row>
  </Worksheet>
</data>